mozjpeg_lossless_optimization/__init__.py
mozjpeg_lossless_optimization/_mozjpeg_opti.pyd
mozjpeg_lossless_optimization/mozjpeg_opti.py
mozjpeg_lossless_optimization/mozjpeg_opti_build.py
mozjpeg_lossless_optimization-1.3.1.dist-info/licenses/LICENSE
mozjpeg_lossless_optimization-1.3.1.dist-info/METADATA
mozjpeg_lossless_optimization-1.3.1.dist-info/WHEEL
mozjpeg_lossless_optimization-1.3.1.dist-info/top_level.txt
mozjpeg_lossless_optimization-1.3.1.dist-info/RECORD
