Metadata-Version: 2.4
Name: mozjpeg-lossless-optimization
Version: 1.3.1
Summary: Optimize JPEGs losslessly using MozJPEG
Home-page: https://github.com/wanadev/mozjpeg-lossless-optimization
Author: Wanadev
Author-email: contact@wanadev.fr
Maintainer: Fabien LOISON
License: BSD-3-Clause
Project-URL: Source Code, https://github.com/wanadev/mozjpeg-lossless-optimization
Project-URL: Documentation, https://github.com/wanadev/mozjpeg-lossless-optimization#usage
Project-URL: Changelog, https://github.com/wanadev/mozjpeg-lossless-optimization#changelog
Project-URL: Issues, https://github.com/wanadev/mozjpeg-lossless-optimization/issues
Project-URL: Chat, https://discord.gg/BmUkEdMuFp
Keywords: image jpeg mozjpeg jpegtran optimization cffi
License-File: LICENSE
Requires-Dist: cffi>=1.0.0
Provides-Extra: dev
Requires-Dist: nox; extra == "dev"
Requires-Dist: flake8; extra == "dev"
Requires-Dist: black; extra == "dev"
Requires-Dist: pytest; extra == "dev"
Dynamic: author
Dynamic: author-email
Dynamic: description
Dynamic: home-page
Dynamic: keywords
Dynamic: license
Dynamic: license-file
Dynamic: maintainer
Dynamic: project-url
Dynamic: provides-extra
Dynamic: requires-dist
Dynamic: summary
